cypher_ai_helper/__init__.py
cypher_ai_helper/main.py
cypher_ai_helper/system_prompt
cypher_ai_helper/user_prompt
cypher_ai_helper/utils.py
cypher_ai_helper-0.1.5.dist-info/LICENSE
cypher_ai_helper-0.1.5.dist-info/METADATA
cypher_ai_helper-0.1.5.dist-info/WHEEL
cypher_ai_helper-0.1.5.dist-info/RECORD
