Metadata-Version: 2.1
Name: cypher-ai-helper
Version: 0.1.5
Summary: A simple helper to create and execute Cypher queries for Neo4j
License: MIT
Author: Trayan Azarov
Author-email: trayan.azarov@amikos.tech
Requires-Python: >=3.10,<4.0
Classifier: License :: OSI Approved :: MIT License
Classifier: Programming Language :: Python :: 3
Classifier: Programming Language :: Python :: 3.10
Classifier: Programming Language :: Python :: 3.11
Requires-Dist: neo4j (>=5.9.0,<6.0.0)
Requires-Dist: openai (>=0.27.8,<0.28.0)
Requires-Dist: pydantic (>=1.10.9,<2.0.0)
Project-URL: Bug Tracker, https://github.com/amikos-tech/cypher-ai-helper/issues
Project-URL: Homepage, https://github.com/amikos-tech/cypher-ai-helper/
Project-URL: Source, https://github.com/amikos-tech/cypher-ai-helper/
